prinpy/__init__.py
prinpy/glob.py
prinpy/local.py
prinpy-0.0.3.1.dist-info/LICENSE
prinpy-0.0.3.1.dist-info/METADATA
prinpy-0.0.3.1.dist-info/WHEEL
prinpy-0.0.3.1.dist-info/top_level.txt
prinpy-0.0.3.1.dist-info/RECORD
