Metadata-Version: 2.1
Name: prinpy
Version: 0.0.3.1
Summary: A package for fitting principal curves in Python
Home-page: https://github.com/artusoma/prinPy
Author: https://github.com/artusoma/
Author-email: artusoma1@gmail.com
License: MIT
Platform: UNKNOWN
Requires-Dist: numpy
Requires-Dist: matplotlib
Requires-Dist: scipy
Requires-Dist: keras
Requires-Dist: tensorflow
